netsink/config.py
netsink/version.py
netsink/start.py
netsink/redirection.py
netsink/__init__.py
netsink/listener.py
netsink/conf/ftp.conf
netsink/conf/irc.conf
netsink/conf/redirection.conf
netsink/conf/smtp.conf
netsink/conf/dispatcher.conf
netsink/conf/ssl.conf
netsink/conf/netsink.conf
netsink/conf/http.conf
netsink/conf/dns.conf
netsink/data/ipaddress.html
netsink/data/ipaddress.txt
netsink/data/privkey.pem
netsink/data/netsink.html
netsink/data/cacert.pem
netsink/data/ftproot/README.txt
netsink/modules/__init__.py
netsink/modules/http.py
netsink/modules/ftp.py
netsink/modules/smtp.py
netsink/modules/sslwrap.py
netsink/modules/ircserver.py
netsink/modules/multi.py
netsink/modules/dns.py
netsink-0.5.dist-info/metadata.json
netsink-0.5.dist-info/entry_points.txt
netsink-0.5.dist-info/DESCRIPTION.rst
netsink-0.5.dist-info/top_level.txt
netsink-0.5.dist-info/METADATA
netsink-0.5.dist-info/WHEEL
netsink-0.5.dist-info/RECORD
