Metadata-Version: 2.0
Name: netsink
Version: 0.5
Summary: Network Sinkhole for Isolated Malware Analysis
Home-page: https://github.com/shendo/netsink
Author: Steve Henderson
Author-email: steve.henderson@hendotech.com.au
License: GPL
Platform: UNKNOWN
Classifier: Development Status :: 4 - Beta
Classifier: Intended Audience :: Developers
Classifier: Intended Audience :: System Administrators
Classifier: License :: OSI Approved :: GNU General Public License v3 or later (GPLv3+)
Classifier: Operating System :: OS Independent
Classifier: Programming Language :: Python
Classifier: Programming Language :: Python :: 2
Classifier: Programming Language :: Python :: 2.6
Classifier: Programming Language :: Python :: 2.7
Classifier: Topic :: Internet
Classifier: Topic :: Security
Requires-Dist: dnslib (>=0.8,<0.9)
Requires-Dist: irc (>=8.0,<10.0)
Requires-Dist: pyftpdlib (>=1.4)
